README.rst
setup.py
stirplate/__init__.py
stirplate/stirplate.py
stirplate.egg-info/PKG-INFO
stirplate.egg-info/SOURCES.txt
stirplate.egg-info/dependency_links.txt
stirplate.egg-info/entry_points.txt
stirplate.egg-info/requires.txt
stirplate.egg-info/top_level.txt
stirplate/species/dna.json
stirplate/species/gbs.json
stirplate/species/rna.json