Metadata-Version: 1.1
Name: stirplate
Version: 1.4.0
Summary: Stirplate Data Uploader
Home-page: https://github.com/stirplate/upload
Author: The Stirplate, Inc. Team
Author-email: brett@stirplate.io
License: MIT
Keywords: stirplate bioinformatics upload biology genetics genomics proteomics rna dna gbs
Platform: UNKNOWN
Classifier: Development Status :: 5 - Production/Stable
Classifier: Intended Audience :: Science/Research
Classifier: Topic :: Scientific/Engineering :: Bio-Informatics
Classifier: License :: OSI Approved :: MIT License
Classifier: Programming Language :: Python
